axis/__init__.py
axis/__main__.py
axis/device.py
axis/errors.py
axis/py.typed
axis/rtsp.py
axis/stream_manager.py
axis/interfaces/__init__.py
axis/interfaces/api_discovery.py
axis/interfaces/api_handler.py
axis/interfaces/basic_device_info.py
axis/interfaces/event_instances.py
axis/interfaces/event_manager.py
axis/interfaces/light_control.py
axis/interfaces/mqtt.py
axis/interfaces/pir_sensor_configuration.py
axis/interfaces/port_cgi.py
axis/interfaces/port_management.py
axis/interfaces/ptz.py
axis/interfaces/pwdgrp_cgi.py
axis/interfaces/stream_profiles.py
axis/interfaces/user_groups.py
axis/interfaces/vapix.py
axis/interfaces/view_areas.py
axis/interfaces/applications/__init__.py
axis/interfaces/applications/application_handler.py
axis/interfaces/applications/applications.py
axis/interfaces/applications/fence_guard.py
axis/interfaces/applications/loitering_guard.py
axis/interfaces/applications/motion_guard.py
axis/interfaces/applications/object_analytics.py
axis/interfaces/applications/vmd4.py
axis/interfaces/parameters/__init__.py
axis/interfaces/parameters/brand.py
axis/interfaces/parameters/image.py
axis/interfaces/parameters/io_port.py
axis/interfaces/parameters/param_cgi.py
axis/interfaces/parameters/param_handler.py
axis/interfaces/parameters/properties.py
axis/interfaces/parameters/ptz.py
axis/interfaces/parameters/stream_profile.py
axis/models/__init__.py
axis/models/api.py
axis/models/api_discovery.py
axis/models/basic_device_info.py
axis/models/configuration.py
axis/models/event.py
axis/models/event_instance.py
axis/models/light_control.py
axis/models/mqtt.py
axis/models/pir_sensor_configuration.py
axis/models/port_cgi.py
axis/models/port_management.py
axis/models/ptz_cgi.py
axis/models/pwdgrp_cgi.py
axis/models/stream_profile.py
axis/models/user_group.py
axis/models/view_area.py
axis/models/applications/__init__.py
axis/models/applications/application.py
axis/models/applications/fence_guard.py
axis/models/applications/loitering_guard.py
axis-66.dist-info/licenses/LICENSE
axis-66.dist-info/METADATA
axis-66.dist-info/WHEEL
axis-66.dist-info/entry_points.txt
axis-66.dist-info/top_level.txt
axis-66.dist-info/RECORD
