Metadata-Version: 2.4
Name: axis
Version: 66
Summary: A Python library for communicating with devices from Axis Communications
Author-email: Robert Svensson <Kane610@users.noreply.github.com>
License: MIT
Project-URL: Source Code, https://github.com/Kane610/axis
Project-URL: Bug Reports, https://github.com/Kane610/axis/issues
Project-URL: Forum, https://community.home-assistant.io/t/axis-camera-component/
Keywords: axis,vapix,homeassistant
Classifier: Development Status :: 5 - Production/Stable
Classifier: Intended Audience :: Developers
Classifier: License :: OSI Approved :: MIT License
Classifier: Operating System :: OS Independent
Classifier: Programming Language :: Python :: 3.13
Classifier: Topic :: Home Automation
Requires-Python: >=3.13.0
License-File: LICENSE
Requires-Dist: faust-cchardet>=2.1.18
Requires-Dist: httpx>=0.26
Requires-Dist: orjson>3.9
Requires-Dist: packaging>23
Requires-Dist: xmltodict>=0.13.0
Provides-Extra: requirements
Requires-Dist: httpx==0.28.1; extra == "requirements"
Requires-Dist: orjson==3.11.5; extra == "requirements"
Requires-Dist: packaging==25.0; extra == "requirements"
Requires-Dist: xmltodict==1.0.2; extra == "requirements"
Provides-Extra: requirements-test
Requires-Dist: mypy==1.19.1; extra == "requirements-test"
Requires-Dist: pytest==9.0.2; extra == "requirements-test"
Requires-Dist: pytest-aiohttp==1.1.0; extra == "requirements-test"
Requires-Dist: pytest-asyncio==1.3.0; extra == "requirements-test"
Requires-Dist: pytest-cov==7.0.0; extra == "requirements-test"
Requires-Dist: respx==0.22.0; extra == "requirements-test"
Requires-Dist: ruff==0.14.10; extra == "requirements-test"
Requires-Dist: types-xmltodict==v1.0.1.20250920; extra == "requirements-test"
Provides-Extra: requirements-dev
Requires-Dist: pre-commit==4.5.1; extra == "requirements-dev"
Dynamic: license-file
